pyhpesse/__init__.py
pyhpesse/adminapi.py
pyhpesse/common.py
pyhpesse/utils_sse.py
pyhpesse-1.0.3.dist-info/METADATA
pyhpesse-1.0.3.dist-info/WHEEL
pyhpesse-1.0.3.dist-info/licenses/LICENSE.md
pyhpesse-1.0.3.dist-info/RECORD
