Metadata-Version: 2.4
Name: pyhpesse
Version: 1.0.3
Summary: HPE Aruba Networking Security Service Edge (SSE) SDK has been developed in Python v3.9 to utilise the full functionality of the HPE Aruba Networking SSE API environment. Each available REST API command is available for use in this module.
Project-URL: homepage, https://developer.arubanetworks.com/pyhpesse/docs/getting-started-with-pyhpesse
Project-URL: repository, https://github.com/aruba/pyhpesse
Project-URL: changelog, https://github.com/aruba/pyhpesse/blob/main/RELEASE-NOTES.md
Author-email: Aruba Automation <aruba-automation@hpe.com>
License-Expression: MIT
License-File: LICENSE.md
Classifier: Development Status :: 5 - Production/Stable
Classifier: Intended Audience :: System Administrators
Classifier: License :: OSI Approved :: MIT License
Classifier: Operating System :: OS Independent
Classifier: Programming Language :: Python :: 3
Classifier: Topic :: System :: Networking
Requires-Python: >=3.9
Requires-Dist: requests>=2.24
Requires-Dist: urllib3>=1.25.10
